[
  {
    "source_id": "40227",
    "consulting_date": "",
    "consulting_category": "부가서비스 안내",
    "client_gender": "",
    "client_age": "",
    "consulting_content": "상담사 일상의 즐거운 변화 LGU NAME입니다\n고객 여보세요\n상담사 네 안녕하세요\n고객 제가 지금 결합을 연결하려고 하는데 데이터가 안되서요 이거 얼마나 나와요\n상담사 아 네 그러면은 핸드폰 데이터로 핫스팟을 켜실 거예요 아니면 와이파이 공유기로 데이터를 이용하실 거예요\n고객 핸드폰이요\n상담사 네 전화 주신 NAME 님 본인 되십니까\n고객 네\n상담사 지금 고객님 사용 중인 요금제가 한 달에 15GB 제공해 드리고 속도가 느려지잖아요\n고객 네\n상담사 그래서 이제 그 빠른 속도로 이용할 수 있는 데이터까지만 핫스팟 연결이 가능하시고 지금은 그 데이터 모두 다 이용하셔서 속도가 느려졌기 때문에 핫스팟 연결이 안 되는 거예요\n고객 아 그래요 그렇게 되나요\n상담사 예 그렇지만 지금 고객님께서 차선책으로 안내를 드리고 싶은데 고객님께서는 저희 LGU 장기 고객님이세요\n고객 네\n상담사 혹시 2배 쿠폰이라고 들어 보셨어요\n고객 뭐 들어본 거 같은데 들어온 게 없는 거 같은데요\n상담사 네 그러면은 오늘 날짜로 그 무료로 2배 쿠폰을 등록을 하게 되면 25GB를 다시 빠르게 이용을 하실 수가 있어요 그러면 핫스팟 연결해서 15GB까지 핫스팟으로 데이터를 이용하실 수가 있습니다\n고객 아 그래요\n상담사 예 그럼 이거 등록해 드릴까요\n고객 이거 무료예요\n상담사 네\n고객 25GB면 몇 시간 정도 사용되나요\n상담사 연속적으로 하면은 1시간 반에서 2시간 정도라고 보시면 돼요\n고객 아 그래요\n상담사 네\n고객 그러면 저기 무료로 쓰면서 나간다는 거예요\n상담사 네 그러면은 오늘 날짜 등록해 드릴 텐데 오늘 등록한 데이터는 30일 동안 이용이 가능하시고 재등록은 30일 이후에 가능하세요\n고객 아 네\n상담사 네 그래서 저랑 전화 끊고 나서 전화를 한번 껐다가 켜서 이제 노트북이나 태블릿으로 핫스팟 연결 시도하시면 정상적으로 이용 가능합니다\n고객 아 네 감사합니다\n상담사 그리고 어렵게 전화 주셨는데 따로 또 궁금하신 점 없으셨어요\n고객 아니요 제가 와이파이 설치를 한다고 했는데 그렇게 급하게 돼서요\n상담사 아 예 그래서 일단은 요금이 더 나오지 않는 무료로 제가 이용하시는 방법을 안내해 드렸구요\n고객 네\n상담사 네 혹시 몰라서 2배 쿠폰 나중에 또 이용하실 때 고객센터어플에서 등록이 가능해서 그 경로 한번 문자 넣어 드릴게요\n고객 네 감사합니다\n상담사 네 우리 고객님 얼마 남지 않은 DATE 누구보다 멋지게 마무리하시기 바라겠습니다\n고객 네 감사합니다\n상담사 감사합니다"
  }
]