[
  {
    "source_id": "40034",
    "consulting_date": "",
    "consulting_category": "휴대폰 정지/분실/파손",
    "client_gender": "",
    "client_age": "",
    "consulting_content": "네 안녕하세요 제가 그 건강상 해외에 출국을 해야 돼서 전화를 드린 거거든요 예 네 네 아니면 6개월이나 DATE에 와요 네 예 네 네 들어왔는데요 확인 네 그럼 잠깐만요 응 알았습니다 그러면 뭐 이거 서류로 그쪽으로 보내면 되는 건가요 그러면은 요거 빨리 알아듣는 우리 딸로 좀 바꿀까요 아 안 되는데 우리가 할 때 아버지 거를 해서 안 돼요 예 아 지금 보낼게요 지금 들고 있어요 아 근데 이상하게 안 들어간다는데요 아 잠깐만요 어떻게 해야 되는 거죠 계속 처리 중이라고 뜨는데 이거 계속 기다려야 되나 예 아 그러면 이게 지금 들어갔는지 확인을 하실 수는 없는 건가요 아 알겠습니다 아 이게 혹시 처리가 되면 문자가 오나요 아 알겠습니다 네 DATE부터요 네 그렇게 해주세요 네 네 감사합니다 아 예 괜찮습니다 네 네 감사합니다 네 감사합니다 네 네"
  }
]