[
  {
    "source_id": "40062",
    "consulting_date": "",
    "consulting_category": "요금 납부",
    "client_gender": "",
    "client_age": "",
    "consulting_content": "네 안녕하세요 요금 관련해서 DATE에 제가 금액하고 계좌번호를 문자로 받을 수 있을까요 예 예 신한 될까요 예 신한으로 해주세요 자동이체 신청하면 알아서 결제 되는건가요 네 아 그래요 그러면요 그 신한은행에 납부할 수 있는 계좌번호하고 금액 좀 문자로 보내주시고 이거 말고 제 꺼는 아닌데 딸 폰도 가능하나요 아 네 문자로요 아 네 MOBILENUMBER MOBILENUMBER네 네 NAME BIRTHNUMBER 아마 카드로 돼있을 거 같은데 제가 근데 입금을 했거든요 계좌이체로 네 제 번호로요 알겠습니다 네 그러면 신한으로 잠시만요 아 네 아 그러면 혹시 인터넷도 LG에서 사용을 하는데 인터넷 결제 계좌번호도 혹시 문자로 받을 수 있는 방법이 있을까요 네 네 수고하세요"
  }
]